{
  "Under 17": {
    "partite": [
      {
        "giornata": 1,
        "squadraA": "ACADEMY",
        "squadraB": "NEW TEAM",
        "data": "9.052025",
        "orario": "19.00",
        "campo": "CAMPO A",
        "girone": "GIRONE A",
        "golA": 3,
        "golB": 1,
        "portiere": "MELADIO' GIOVANNI",
        "giocatore": "GOBBI ALESSANDRO",
        "marcatori": [
          {
            "nome": "Susin",
            "gol": 3,
            "squadra": "A"
          },
          {
            "nome": "Ciccio",
            "gol": 1,
            "squadra": "B"
          }
        ]
      },
      {
        "giornata": 2,
        "squadraA": "ACADEMY",
        "squadraB": "CIRCOLO MASTER",
        "data": "12.05.2025",
        "orario": "20.00",
        "campo": "CAMPO B",
        "girone": "GIRONE A",
        "golA": 2,
        "golB": 0,
        "portiere": "KIKKO",
        "giocatore": "GOBBI ALESSANDRO",
        "marcatori": [
          {
            "nome": "Susin",
            "gol": 1,
            "squadra": "A"
          },
          {
            "nome": "IANCU",
            "gol": 1,
            "squadra": "A"
          },
          {
            "nome": "TITA",
            "gol": 1,
            "squadra": "B"
          }
        ]
      }
    ],
    "gironi": {
      "GIRONE A": [
        "ACADEMY",
        "NEW TEAM",
        "CIRCOLO MASTER"
      ],
      "GIRONE B": [
        "FORTITUDO",
        "ARDEA",
        "ECOCITY"
      ]
    },
    "finali": []
  },
  "Under 15": {
    "partite": [],
    "gironi": {},
    "finali": []
  },
  "Under 13": {
    "partite": [],
    "gironi": {},
    "finali": []
  },
  "2014/15": {
    "partite": [],
    "gironi": {},
    "finali": []
  },
  "2016/17": {
    "partite": [],
    "gironi": {},
    "finali": []
  },
  "Under 15 femminile": {
    "partite": [],
    "gironi": {},
    "finali": []
  },
  "Under 13 femminile": {
    "partite": [],
    "gironi": {},
    "finali": []
  }
}